{
  "height": 11,
  "legend": {
    "!": "313131ff",
    "#": "313133ff",
    "$": "313233ff",
    "%": "313334ff",
    "&": "323232ff",
    "'": "333333ff",
    "(": "353535ff",
    ")": "363636ff",
    "*": "496abaff",
    "+": "498adbff",
    ",": "4a6abbff",
    "-": "4a6bbdff",
    ".": "4a6cbeff",
    "/": "4a8bdbff",
    "0": "4a8bddff",
    "1": "4a8cdeff",
    "2": "4b8cddff",
    "3": "4c6cbbff",
    "4": "4c8cdcff",
    "5": "4c8ddcff",
    "6": "515151ff",
    "7": "515253ff",
    "8": "515254ff",
    "9": "525252ff",
    ":": "525354ff",
    ";": "535353ff",
    "<": "545453ff",
    "=": "62bafbff",
    ">": "62bbfcff",
    "?": "62bbfdff",
    "@": "62bcfeff",
    "A": "63bdfdff",
    "B": "63bdffff",
    "C": "65bdfdff",
    "D": "65beffff",
    "E": "838383ff",
    "F": "848484ff",
    "G": "9abbbbff",
    "H": "9dbdbcff",
    "I": "babab2ff",
    "J": "bbbbb3ff",
    "K": "bcbcb4ff",
    "L": "bdbdb5ff",
    "M": "cbba71ff",
    "N": "cbbb74ff",
    "O": "ccbb72ff",
    "P": "cebd73ff",
    "Q": "ece49aff",
    "R": "eee69bff",
    "S": "efe79cff",
    "T": "fbfbfbff"
  },
  "name": "pokemon-sprite-I-131-lapras",
  "pixels": [
    "   (!   (!              ",
    "  )*-#!!=B%             ",
    " )!*79,?BBB%            ",
    ")=18>B.?.?B%            ",
    " )=B.?BB.?1$            ",
    " )*?BBB11-!             ",
    "  )=BB%TD1$   )!!       ",
    " )=BB:!=.0$ )!ILL'!     ",
    " (=BBB.-N37!ILFKLLF&    ",
    "  )=1-NPP3-7EKLLFKL'    ",
    "   )!!!MP308JFKLLLLF&   ",
    "       )MP418JFKLFFK'   ",
    "       )QS5@:JFFFKL;!   ",
    "       )QSHAB:JLL;9/$!  ",
    "      )MRSSCBB:99/1111$ ",
    "    )!6QSSSHA1111-#*011$",
    "   (*08ORSSS</189! (!!! ",
    "  )+1-#!MRS<G211@:!     ",
    "   )!!  (!!6ORHABBB%    ",
    "            )!QSHABB%   ",
    "              )!!!!!    "
  ],
  "width": 24
}
