{
  "height": 11,
  "legend": {
    "!": "313131ff",
    "#": "313232ff",
    "$": "313233ff",
    "%": "323333ff",
    "&": "333332ff",
    "'": "333333ff",
    "(": "343434ff",
    ")": "353535ff",
    "*": "363636ff",
    "+": "388aabff",
    ",": "398babff",
    "-": "398cadff",
    ".": "3a8daeff",
    "/": "3b8cabff",
    "0": "3b8dacff",
    "1": "515151ff",
    "2": "515253ff",
    "3": "525252ff",
    "4": "525253ff",
    "5": "525354ff",
    "6": "525454ff",
    "7": "52729aff",
    "8": "52739cff",
    "9": "52739dff",
    ":": "52749dff",
    ";": "535351ff",
    "<": "535353ff",
    "=": "53749cff",
    ">": "545452ff",
    "?": "545454ff",
    "@": "54759dff",
    "A": "62abe4ff",
    "B": "62ace5ff",
    "C": "63ade7ff",
    "D": "82dbecff",
    "E": "82dcedff",
    "F": "83dbecff",
    "G": "83dcedff",
    "H": "83ddeeff",
    "I": "84deefff",
    "J": "85deefff",
    "K": "baa341ff",
    "L": "baa443ff",
    "M": "bababaff",
    "N": "bbbbbcff",
    "O": "bca544ff",
    "P": "bda542ff",
    "Q": "bda643ff",
    "R": "bdbdbdff",
    "S": "bebebeff",
    "T": "ece482ff",
    "U": "ece483ff",
    "V": "ede685ff",
    "W": "eee582ff",
    "X": "efe784ff",
    "Y": "fbfbfbff",
    "Z": "fcfcfcff",
    "[": "fcfcfdff",
    "]": "fdfdfdff",
    "^": "ffffffff"
  },
  "name": "pokemon-sprite-I-134-vaporeon",
  "pixels": [
    "                *!!    ",
    "    )           *DC$!!!",
    "   )+#   )!!    )DI6FI%",
    "   *+# *!+--#    )AHIC$",
    "  *K/2!+-LW&     )+2!! ",
    "  *T02,-LW&     *+E%   ",
    "  *T>,-2UX0#   *1,E%   ",
    "  *13,------#!!!+EC$   ",
    " )M'D.-EI.23,---2AC$   ",
    " )1ZJCHIII.-LPP;AC$    ",
    ")M<!DIIC5FOPWX>AC9#    ",
    "*Y?FII:[(AHVQ;7GC$     ",
    " *M=GI:#AC533Z@GI%     ",
    " *Y?7BCC98NR]@GII%     ",
    "  *YS<337N]^@4AHCC$    ",
    "   *!Y^S]^?AC$!!AC$    ",
    "     *!A57GI%   *A$    ",
    "      *A5FI%    *!     ",
    "     )A94FC$           ",
    "      *!DI%            ",
    "        *!             "
  ],
  "width": 23
}
