{
  "height": 32,
  "legend": {
    "!": "000848",
    "#": "101010",
    "$": "283860",
    "%": "405078",
    "&": "604810",
    "'": "6088b0",
    "(": "a08848",
    ")": "d0c068",
    "*": "e80800",
    "+": "f86000",
    ",": "f89800",
    "-": "f8d800",
    ".": "f8e890",
    "/": "f8f8c0",
    "0": "f8f8f8"
  },
  "name": "pokemon-emerald-II-157-typhlosion",
  "pixels": [
    "               *         **                          ",
    "             * **       ***         *****            ",
    "   **        **+**     *++*     ****++-*             ",
    "   *-**      *-,+**   *+++*  ***+++,--*              ",
    "    *--**    *--,+** *++,+***++++,---*               ",
    "     *---** $$$$$!!!*+++-+++++,----**                ",
    "      *,--$$%%%%%%%$!!!--++,----,++++++++            ",
    "    ****$$%%%%%%%%%%%%%!!------,+++++***             ",
    " $!  **$%%%%!!%%%%%%%%%%%!(-------,****              ",
    " $'!  $%%%%!'!%%%%%%%%%%%%%(,---,***********         ",
    " $'%!$''%%%!'!%%%%%%%%%%%%(,--,***********           ",
    " $'%!$''%%!'%!%%%%%%%%%%%%%%(-----,,****             ",
    " $'%$'''%%!'%!%%%%%%%%%%%%%(,----,****               ",
    " $'$''''%!'%%%%%......%%%%%%((-*****                 ",
    " $'$''''%!'%%...........%%%(,,--++++**********       ",
    " $$''''%%%%%.............%%%,----,+++++*****         ",
    " $$''''%%%................%*-,************           ",
    " $''''%%%..((..............*,-,*********             ",
    " $%''%%%..!0(.............************               ",
    " $%%%%%%.!*0.............***************             ",
    " $(%%%%..!*.............****+*++++!                  ",
    " $(%%%%....((()........**.*+*******!                 ",
    "  ()%%...((+*&............*.....%%%!                 ",
    "  !.....(*+++&..()).............&&%%!                ",
    "   !...(0&+++&.()))).............)&%!                ",
    "    ((( (&*++&.())))..............)&%!               ",
    "        (0**0)&)())................)&!               ",
    "       &.&(()&..(..................))&               ",
    "      &./.&&&.))(...................))&              ",
    "     (.//....)))(............).......))(             ",
    "    (.//....))))(..........).(........))(            ",
    "   (.//...))))##(../........))(.......)))&           ",
    "  (......)))#&  (.//..........)(.......)))#          ",
    " &......))#&    &./............)&(.....)))&          ",
    " (.....)#&      &/./...........)))&(..)))))#         ",
    "&.(.())&        &//.............)))$&&)))))#         ",
    "&.()(#&         &/./............)))$&))&)))#         ",
    "(..###          &//.............))))$&&)))(#         ",
    " (.(#(#        &)/./.............)))$&))&(#          ",
    "  ())#         &)//..............)))$$&&(&#          ",
    "   &#          (//./.............))))$####           ",
    "              &(///...............)))$$$$$#          ",
    "              ((//./..............))))$$$$!          ",
    "             &)(/./...............))))$$$$$#         ",
    "            (..)//.................))))$$$$!         ",
    "           (//.)/..................).)))$$$$#    !!  ",
    "           (//......................).)))$$$!  !!!   ",
    "          (//........................).))($$$!!$$#   ",
    "          (././.......................))))($$!$$!    ",
    "         (././.......................).))))$$$!!###  ",
    "         (/./.........................)))))($$$!$!   ",
    "         (...........................).))))($$$$!##  ",
    "         (..........................).)))))($$$$$#   ",
    "         &...........................))))))($$$$$$!  ",
    "         &).........))))))))........)))))))$$$$$$$$# ",
    "          &(......))))))))))))....)))))))))&$$$$$###!",
    "           &(...))))((((&&&&()))))))))))))(($$$$$#   ",
    "         &&....)))(((((((((&&&&(())))))))(()($$$$$#  ",
    "        &.....))(####&&&&&&&######())))))))))(&$###  ",
    "       &.....(###                 ####()))))))(&#    ",
    "      &(.(.(##                        #&())))))(#    ",
    "      ######                            #())()()#    ",
    "                                         #&()()(#    ",
    "                                           #####&    "
  ],
  "width": 53
}
