{
  "height": 29,
  "legend": {
    "!": "101010",
    "#": "603860",
    "$": "686868",
    "%": "886800",
    "&": "989898",
    "'": "a05098",
    "(": "c0a028",
    ")": "c878b8",
    "*": "d0d0d0",
    "+": "e898d0",
    ",": "f8f888",
    "-": "f8f8f8"
  },
  "name": "pokemon-emerald-II-214-heracross-shiny",
  "pixels": [
    "                         ''                                    ",
    "            ''          '+'                                    ",
    "            '+'        '+'#                                    ",
    "            '+#        '+'#                                    ",
    "            '++'      '+)'#                                    ",
    "            #++#     '++''#                                    ",
    "            #+++#   '++)'!                                     ",
    "             '+)+###++)''!                                     ",
    "             #+))++++)'''!                                     ",
    "              '))++))''''!                                     ",
    "              ')'++)''''''#                                    ",
    "              #)'#+)!!!!''!                                    ",
    "              #)##+)'#  !!!                                    ",
    "              ### '+''!                                        ",
    "                  #+)'!  ''######                              ",
    "                  #+)''!#)+++)'''###                           ",
    "              ''#  ')''#)++++))'#++)!                          ",
    "             '++'# #+)''!+++)))'#+)'!#                         ",
    "             '+)'# !+)'''####')'#)''!'#                        ",
    "             ')''#  #+)''##++)))'!!!'''#                       ",
    "              ###' #!+))''!!)''!'!'''''!                       ",
    "                #)##!++))'''''#'!'''''''#                      ",
    "                 #)'#!++))'''''##'''''''!                      ",
    "        ###       ##'!+++))''''%%%'''''''#                     ",
    "      ##)&*&      '+##+++))'''%--(%''''''!                     ",
    "     #+)#*-*&     '+%-!++))'''(-!,!'''''##!                    ",
    "    #+*-&#-*$     #+%-!'))'''%,!!(!''''#++)#!!    ##!!!        ",
    "   '#)--*'#*$     #+%,!''''''%,!!!''''#++++)'#####+))))#!!     ",
    " '#+#)#--#'!!     #++%(#'++)'%%((!''''#+++))!)))!+++)))'''##   ",
    "'++))###*#'!     ##++)##)+)))'#!!'''''!)))''#'''!#++))'''#''#  ",
    "#)'''+''##'!     #)#+))##)!#''!'''''''!''''''#!!#++#!!!''!!!!  ",
    " ##''+)''''!    #))#+)))!!''!!''''''''!#'''!!! #++#+++'!''#    ",
    "   ##)))'''!   #)))'#))))))''''''''''!''!!!#!  #+#+++)''!'''#  ",
    "    #'))'''!   ##))'#))'#######'''''!''''#'#!  #+##))#!'!''''' ",
    "  ''+'+))''! ##)'!''!''#'''''''#!!!!'''''#''#!  #-&'#-&'!'#####",
    "  #+))+))'''#))'!!!! ##'''))))''##''''''''!'#! $--*'*-*#''!!!!!",
    "   ##')))'''!'!!      #+')))))))'#''''''''!'#! $-*&#&-*!!!     ",
    "     ##)'''!!!        #+)')))))))#''''''''!!!!!#-&! $*&!       ",
    "       #!!!            #+'))))))))#'''''''!'''##*#! $*!        ",
    "                   ### #+)')))))))#''''''#)'''''#'!  !         ",
    "                   #))!'#+')))))))'#''''#)++)'''''!            ",
    "                   #)!))!+)')))))''#''''#)+++)''#!             ",
    "                   #!)++)#+')))))'''#'''#)++++)''#             ",
    "                   #)+++)!+)'))'''''#'''#))+++)'''!            ",
    "                   #)+))''#+'''''''''#'''!!)++)'''!            ",
    "                   #))''''!!!'#######'#'#! !))''''!            ",
    "                   #''''#!!! ##''''''##!!   ##'''!!            ",
    "                    #!!!'!     #!!!!!!!     #'#!!#!            ",
    "                     #))'#                   #''##!            ",
    "                    '##!!#!                  )##!!'!           ",
    "                   '))))'#!                  #)))'''!          ",
    "                  &--#)'#!                   #))'##'!          ",
    "                 &--**##!                     ###-**!          ",
    "                $***#!!                        #*--*$          ",
    "                ##!!                            !!--&!         ",
    "                                                  !!&!         ",
    "                                                    !!         "
  ],
  "width": 63
}
