{
  "height": 66,
  "legend": {
    "!": "color023",
    "#": "color058",
    "$": "color059",
    "%": "color065",
    "&": "color066",
    "'": "color073",
    "(": "color094",
    ")": "color095",
    "*": "color100",
    "+": "color101",
    ",": "color107",
    "-": "color108",
    ".": "color109",
    "/": "color115",
    "0": "color136",
    "1": "color137",
    "2": "color142",
    "3": "color143",
    "4": "color144",
    "5": "color149",
    "6": "color150",
    "7": "color151",
    "8": "color179",
    "9": "color185",
    ":": "color186",
    ";": "color236",
    "<": "color237",
    "=": "color238",
    ">": "color239",
    "?": "color240"
  },
  "name": "monster-hunter-MH10th-zinogre-icon",
  "pixels": [
    "                                                                                                                                  ",
    "                                                                                        :::                ::      ''             ",
    "                                                                                       ::::                ::    '''              ",
    "                                                                                      :::::               :::   '''               ",
    "                                                                                     ::::::              ::::  '''                ",
    "                                                                                    :::::::             :::::/'''                 ",
    "                                                                                   ::::::::            :::::/'''                  ",
    "                                                                                  :::::::::            ::::/'''                   ",
    "                                                                                 ::::::::::           ::::7'''                    ",
    "                                                                                :::::::::::          ::::6'''/                    ",
    "                                                                               ::::::::::::         ::::6'''/:                    ",
    "                                                                              :::::::::::::         :::6'''/::                    ",
    "                                                                             ::::::::::::::        :::6.''/:::                    ",
    "                               (                                            :::::::::::::::       ////.''/::::                    ",
    "((((((((((*000000000000000000((((*00000000((((00000000000000*((((*0000*((((3:::::::::::::::  '''''''''''/:::::                    ",
    "((((((((((((*0000000000000000(((((*0000000*((((000000000000*(((((0000*((((03::::::::::::::: '''''''''''/::::::                    ",
    "  (((((((((((*000000000000000((((((00000000(((((*000000000*(((((*000*((((009::::::::::::::6.''''''''''/:::::::::                  ",
    "   ((((((((((((*0000000000000*(((((*0000000*((((*00000000*((((((0000((((*009::::::::::::::.''''''''''/::::::::::::::::::::::::    ",
    "     ((((((((((((*000000000000(((((000000000((((*00000000((((((*0000(((*000::::::::::::::/''''''''''/:::::::::::::::::::::::::    ",
    "       ((((((((((((*0000000000*((((000000000*(((*0000000*((((((00000(((*000:::::::::::::/''''''''''/:::::::::::::::::::::::::     ",
    "         ((((((((((((0000000000((((*000000000(((*0000000((((((*00000(((0003::::::::::::7''''''''''/:::::::::::::::::::::::::      ",
    "           (((((((((((*000000000((((000000000*((*000000*((((((000000(((0003:::::::::::6''''''''''/:::::::::::::::::::::::::       ",
    "             (((((((((((*0000000*((((000000000((*00000*((((((*000000*((0003::::::::::6''''''''''/:::::::::::::::::::::::::        ",
    "               (((((((((((*000000*(((*00000000((*00000(((((((*?>>>>>>>>?%%3:::::::::6.'''''''''/:::::::::::::::::::::::::         ",
    "                 (((((((((((*00000((((00000000((000000((((((%=!!!!!!!!!!!!3:::::::::/'''''''''/:::::::::::::::::::::::::          ",
    "                   ((((((((((*00000(((*0000000((000000((((#>!!!!!!!!!!!!!>6::::::::/'''''''''/:::::::::::::::::::::::::           ",
    "                     ((((((((((*000*(((*00000*((00***%>#(>=!!!!!!!!!!!!!>3::::::::/'''''''''/91(((*23333333893335:::::            ",
    "                       (((((((((*000*(((00000*((>!!!!!!!=!!!!!!!!!!!!!!!3::::::::6'''''''''-30*(((00000000000(((((3::             ",
    "                         ((((((((0000*((*0000*((>!!!!!!!!!!!!!!!!!!!!!!,::::::::6''''''''.,000((((0000000000*((((008:             ",
    "                           ((((((00000(((0000*(#!!!!!!!!!!!!!!!!!!!!!!,::::::::6.''''./6300000((((000000000*((((00009:            ",
    "                           !!!!!!!!!!!!!!!!!!;;;<!!!!!!<;;;;;;!!!!!!!,:::::::::.'''''930000000((((000000000((((0000029:           ",
    "                           !!!!!!!!!!!!!!!!!!<;;;<!!!!<;;;;;;;!!!!!!+:::::::::/'''''',00000000((((00000000((((00000003::          ",
    "                          !!!!!!!!!!!!!!!!!!!!;;;;<!!<;;;;;;;;!!!!!%:::::::::/''''''',00000000((((0000000((((*000000003::         ",
    "           ;<!!!!!!!!!!!!!!!!!!!!<<<<;>%%+>!!!<;;;;;;;;;;;;;;!!!!!%:::::::::7''''''+)*00000000((((000000*(((*00000000008::        ",
    "          ;;;<!!!!!!!!!!!!!!!!!!;;;;;<00000*?!!;;;;;;;;;;;;;!!!!!%:::::::::6'''.,+(((*0000000*((((00000*(((*000000000003:::       ",
    "           ;;;<!!!!!!!!!!!!!!!<;;;;;;*0000000*%=;;;;;;;;;>?%%+++3:::::::::6'.-1000(((*0000000*(((*00000(((*0000000000003::::      ",
    "            ;;;<!!!!!!!!!!!!!<;;;;;;#00000000000*%3335::::::::::::::::::::3,000000(((*000                 00000000000003:::::     ",
    "            ;;;;<!!!!!!!!!!!!;;;;;;<000000000000009::::::::::::::::::::::30000000*(((000                   0000000000003::::::    ",
    "             ;;;;!!!!!!!!!!!!;;;;;;00000000000000009::::::::::::::::::::300000000*(((00                     000000000003:::::::   ",
    "              ;;;;!!!!!!!!!!!<<<<<*000000000000000009::::::::::::::::::3000000000*(((0                       00000000003::::::::  ",
    "               ;;;;!!!!!!!!=*0000000000000000000000008::::::::::::::::1*000000000*(((  !!!!!!!!!!!!!!!        0000000003::::::::: ",
    "                ;;;;!!!!!!=*000000000000000000000000008::::::::::::::3(*000000000*((  !!!!!!>=!!!!!!!!!!      *0000000029:::::::: ",
    "                ;;;;;!!>>??******0000000000000000000000:::::::::::::3((*000000000*(  !!!!!=+0*!!!!!!!?+*!     (*0000000000233399: ",
    "                 ;;=#*000((((((((((((*00000000000000000::::::::::::3(((*000000000*  !!!!!!+000+!!!!!>000>!!   ((*0000000000000000 ",
    "                 *000000*(((((((((((((00000000000000000:::::::::::30(((*000000000  !!!!!!!>000*!!!!!=*00>!!   (((*000000000000000 ",
    "              000000000*((((((((((((((00000000000000000%6::::::::300(((*00000000  !!!!!!!!!?+*>!!!!!!>*?=!!   ((((*0000000000000  ",
    "             0000000000((((((((        0000000000000000!>,::::::3000(((*0000000  !!!!!!!!!!!!!!!!!!!!!!!!!!   (((((*00000000000   ",
    "            0000000000((((              000000000000000>!!?3:::30000(((*000000  !!!!!!!!!!!!!!!!!!!!!!!!!!!   ((((((*000000000    ",
    "           00000000                      00000000000000>!!!!+:300000(((*00000  !!!!!!?%?!!!!!!!!!!!!!!!!!!!   (((((((*0000000     ",
    "          0000                            0000000000000>!!!!=+000000(((*0000   !!!!=*00*!!!!!!!!!!!!!!!!!!!   ((((((((*0000       ",
    "         0000                    '         000000000000>!!!=?*000000(((*000   !!!!!+000*!!!!!!!!!!!!!!!!!!!   0*(((((((*00        ",
    "           0                    ''          00000000000>!!=?(*000000(((*00   !!!!!!>000*!!!!!!!!!!!!!!!!!!!   000*((((((*2        ",
    "                               ''            0000%?>>!!!!!>(((000000(((*0   !!!!!!!!%0*%!!!!!!!!!!!!!!!!!!!   0000*(((((+::       ",
    "                              '''             00*!!!!!!!!!>(((000000(((*   !!!>!!!!!=>!!!!!!!!!!!!!!!!!!!!!   000000*(((3:::      ",
    "                             ''''             00+!!!!!!!!!>(((000000(((   !!!%0*>!!!!!!!!!!!!!!!!!!!!!!!!!!   0000000*((3::::     ",
    "                            '''''              0%!!!!!!!!>*(((000000((   !!!>0000+!!!!!!!!!!!!!!!!!!!!!!!!!   000000000*3:::::    ",
    "                           '''''                ?!!!!!!!>00(((000000(   !!!!%0000*!!!!!!!!!!!!!!!!!!!!!!!!!   0000000000:::::::   ",
    "                          ''''''                 !!!!!!>000(((000000   !!!!!!+000*!!!!!!!!!!!!!!!!!!!!!!!!!   00000000009:::::::  ",
    "                         ''''''                   !!!!>0000(((00000   !!!!!!!!+00%!!!!!!!!!%%%?!!!!!!!!!!!?   00000000009:::::::: ",
    "                        '''''''                    !!>00000(((*000   !!!!!!!!!!>!!!!!!!!!!?:::+!!!!!!!>3:::   00000000009:::::::::",
    "                        ''''''                      >000000(((*00   !!!!!!!!!!!!!!!!!!!!!>3:::+!!!!!!!3::::   (0000000009:::::::: ",
    "                         ''''                       0000000(((*0   !!!!!!!!!!!!!!!!!!!!!!3::::+!!!!!!,:::::   ((0000000039::::::: ",
    "                          '''''                     0000000(((*   !!!!!*000!!!!!!!!!!!!!+:::::+!!!!!%::::::   (((0000000000033339 ",
    "                           '''''                   0000000*(((   !!!!!?0000=!!!!!!!!!!!%::::::+!!!!%:::::::   ((((000000000000000 ",
    "                            '''''                 00000000*((   !!!!!!>0000>!!!!!!!!!!?:::::::+!!!?::::::::   (((((00000000000000 ",
    "                             '''''               000000000*(   !!!!!!!!?000>!!!!!!!!!>3:::::::+!!>6::::::::   ((((((0000000000000 ",
    "                '''''''       '''''        (((((((((000000*   !!!!>!!!!!??=!!!!!!!!!!,::::::::+!>3:::::::::   (((((((*0000000000  ",
    "               '''''''''       '''''     ((((((((((((0000    !!!>*0?!!!!!!!!!!!!!!!!%:::::::::+!,::::::::::   ((((((((*0000000    ",
    "             ''''''''''''       ''''''   (((((((((((((00    !!!!?000>!!!!?******+%%%3333399999++9::::::::::   0*(((((((*00000     ",
    "             ''''''''''''       ''''''   ((( 0000000000    !!!!!%000+!!!?00000000000000000000000000000009::   00*(((((((0000      ",
    "             ''''''''''''       ''''''   ((( 000000000    !!!!!!*000>!!>0000000000000000000000000000000003:   0000((((((000       ",
    "             ''''''''           ''''''   ((   0000000    !!!!!!!>+0+!!>000000000000000000000000000000000002   00000(((((029:      ",
    "             ''''''            '''''''   ((    00000    !!?0*>!!!!>>!=*000000000000000000000000000000000000   000000*(((39::      ",
    "             ''''''           '''''''' ((((     000    !>*0000?!!!!!!*0000000000000000000000000000000000000   0000000*((3::::     ",
    "              ''''''         ''''''''  (((             ?0000000+=!!!+00000000000000000000000000000000000000   000000000(3:::::    ",
    "               ''''''       ''''''''    (             >000000000%!!>0000000000%>>>>>>>>>>>>>>>>>>?000000000   00000000003::::::   ",
    "                '''''''    ''''''''       ::::::     !!000000000%!!>000000000+!!!!!!!!!!!!!!!!!!!!%00000000   00000000003:::::::  ",
    "                 '''''''  ''''''''       ::::::::   !!!*00000000+!!>00000000+!!!!!!!!!!!!!!!!!!!!!!+0000000   00000000003:::::::  ",
    "                  '''''''''''''''       :::::::::  !!!!>00000000?!!>0000000*!!!!!!!!!!!!!!!!!!!!!!!=?%**000   00000000003:::::::: ",
    "                   '''''''''''''       ::::::::::>!!!!!!>*00000+!!!>0000000+!!!!!!!!!!!!!!!!!!!!!!!!!!!!!>?   *0000000003:::::::: ",
    "                    '''''''''''         :::::::::!!!!!!!!=*000*!!!!>0000000%!!!!!!!!!!!!!!!!!!!!!!!!!!!!!!!   (*000000003:::::::: ",
    "                     '''''''''           ::::::::!!!!!!!!!!>?%=!!!!?0000000%!!!!!****000+!!!!!!!!!!!!!!!!!!   ((*0000000000333339 ",
    "                      '''''''            ::::::::?!!!!!!!!!!!!!!!!!%0000000%!!!!!00000000?!!!!!!!!!!!!!!!!!   ((((0000000000000000",
    "                       ''''               :::::::%!!!!!!!!!!!!!!!!!%0000000?!!!!!000000000?!!!!!!!!!!!!!!!!   (((((00000000000000 ",
    "                                           ::::::%!!!!!!!!!!!!!!!!!%0000000>!!!!!*000000000!!!!!!!!!!!!!!!!   ((((((0000000000000 ",
    "                                            ::::::3>!!!!!!!!!!!!!!!%0000000>!!!!!!!>?%*0000!!!!!!!!!!!!!!!!   (((((((*0000000000  ",
    "          0000         000                  ::::::::%!!!!!!!!!!!!!!%0000000>!!!!!!!!!!!0000!!!!!!!!!!!!!!!!   ((((((((*00000000   ",
    "          00000        0000                  ::::::::,>!!!!!!!!!!!!%0000000>!!!!!!!!!!!0000!!!!!!!!!!!!!!!!   (((((((((*000000    ",
    "         0000000       00000                 :::::::::6?!!!!!!!!!!!%0000000!!!!!!!!!!!!0000!!!!!!!!!!!!!!!!   0(((((((((0000      ",
    "         00000000      000000                :::::::::::+!!!!!!!!!!%0000000?!!!!!!!!!!!000*!!!!!!!!!!!!!!!!   00*(((((((000       ",
    "        0000000000     00000000               :::::::::::%!!!!!!!!!*00000000>!!!!!!!!!!000*!!!!!!!!!!!!!!!!   0000((((((00        ",
    "        00000000000    000000000               :::::::::::?!!!!!!!!*000000000>!!!!!!!!!000*!!!!!!!!!!!!!!!!   00000*((((29:       ",
    "       000000000000    000000000                ::::::::::3>!!!!!!!!+000000000>!!!!!!!!000*!!!!!!!!!!!!!!!!   0000000((+::::      ",
    "                 00                              ::::::::::,!!!!!!!!!?0000000000**%%?>>000*!!!!!!!!!!!!!!!!   00000000*+:::::     ",
    "                                                  ::::::::::%!!!!!!!!!?0000000000000000000?!!!!!!!!!!!!!!!!   0000000003:::::     ",
    "                                                   ::::::::::?!!!!!!!!!>*0000000000000000*!!!!!!!!!!!!!!!!!   0000000002::::::    ",
    "                                                    :::::::::3>!!!!!!!!!=*000000000000000?!!!!!!!!!!!!!!!!!   0000000000:::::::   ",
    "                                                     :::::::::,!!!!!!!!!!!+0000000000000*!!!!!!!!!!!!!!!!!!   0000000000::::::::  ",
    "                                                      :::::::::%!!!!!!!!!!!>>>>>>>>>>>>>>!!!!!!!!!!!!!!!!!!   0000000000::::::::: ",
    "       00000000000000000000000000                      :::::::::?!!!!!!!!!!!!!!!!!!!!!!!!!!!!!!!!!!!!!!!!!!   (000000000::::::::: ",
    "      00000000000000000000000000000                      :::::::3!!!!!!!!!!!!!!!!!!!!!!!!!!!&&&$>!!!!!!!!!!   ((000000009:::::::: ",
    "    00000000*%>>>>>0000>>>>!%000000000                    :::::::,!!!!!!!!!!!!!!!!!!!!!!!!!&'''''!!!!!!!!!!   (((0000000000023333 ",
    "    00000000%!!!!!>0000!!!!!%000000000                     :::::::%!!!!!!!!!!!!!!!!!!!!!!!?''''''!!!!!!!!!!   ((((0000000000000000",
    "    00000000%!!!!!>0000!!!!!%00000000                       :::::::?!!!!!!!!!?>!!!!!!!!!!!&''''''&!!!!!!!!   ((((((00000000000000 ",
    "         000%!!!!!>0000!!!!!%0000000                         99999:3!!!!!!!!>00%=!!!!!!!!!!''''''&!!!!!!!    (((((((0000000000    ",
    "         000%!!!!!>0000!!!!!%000000       000                00008::,!!!!!!!*0000?!!!!!!!!!?'''''?!!!!!!    00(((((((000000000    ",
    "         000%!!!!!>0000!!!!!%00000       0000               000003:::%!!!!!%000000+!!!!!!!!!&''''!!!!!!    0000(((((((0000000     ",
    "         000%!!!!!>0000!!!!!%0000        00000             0000002::::?!!!>00000000+!!!!!!!!!$$!!!!!!!!   000000(((((((000000     ",
    "         000%!!!!!>0000!!!!!%0000       0000000           000000009:::3!!!*000000000+!!!!!!!!!!!!!!!!!   00000000(((((((0000      ",
    "        0000%!!!!!>0000!!!!!%0000      00000000           000000008::::+!?00000000000+=!!!!!!!!!!!!!!   0000000000(((((((000      ",
    "     0000000%!!!!!>0000!!!!!%000       000000000         0000000003:::::%0000000000000+!!!!!!!!!!!!!   000000000000(((((((00      ",
    "   000000000%!!!!!>0000!!!!!%000      00000000000       00000000002:::::300000000000000=!!!!!!!!!!!   00000000000000(((((((       ",
    "   000000000%!!!!!>0000!!!!!%000     00000000000       0000000000009:::8000000000000000?!!!!!!!!!!   0000000000000000((((((       ",
    "   000000000%!!!!!>0000!!!!!%000    ,,,,,3333333      333333333333334443330000000000000*!!          000000000000000000((((5       ",
    "       00000%!!!!!>0000!!!!!%000.'''''''''''''''''''''''''''''''''''''''''''''''''''''''''''''3000000000000000000000000((3:       ",
    "         000%!!!!!>0000!!!!!%00,.'''''''''''''''''''''''''''''''''''''''''''''''''''''''''''''300000000000000000000000003::       ",
    "         000%!!!!!>0000!!!!!?0000,.'''''''''''''''''''''''''''''''''''''''''''''''''''''''''''30000000000000000000000008:::       ",
    "         000%!!!!!>000*!!!!!>000000,.''''''''''''''''''''''''''''''''.''''''''.'''''''''''''''3000000000000000000000008::::       ",
    "         000%!!!!!>000*!!!!!>00000000,'''''''-33,,,,,-''''''',00000000.'''''''300000013333.''',00000000000000000000008:::::       ",
    "         000%!!!!!>000*!!!!!>000000000''''''',00000000'''''''-00000000-'''''''300000000000-''',0000000000000000000003::::::       ",
    "        0000%!!!!!>000*!!!!!>000000000-''''''300000000-''''''-00000000-''''''',00000000000,''',000000000000000000003:::::::       ",
    "       00000%!!!!!>000*!!!!!>000000000-''''''.10000000-''''''.00000000-'''''''',00000000001'''-00000000000000000003::::::::       ",
    "      000000%!!!!!>000*!!!!!=000000000,'''''''.,000000,'''''''00000000,''''''''',0000000000.'''-1000000000000000029::::::::       ",
    "     0000000%!!!!!>0000>!!!!!>000000001.'''''''',000001-''''''-,0000000,.'''''''',000000000,''''',0000000000000029:::::::::       ",
    "    00000000%!!!!!>00000>!!!!!?000000000,-''''''.00000003-''''''.000000003-'''''',0000000000-'''',000000000000029::::::::::       ",
    "    00000000%!!!!!>000000>!!!!!*00000000000,.'''-0000000001-'''''00000000001-.'''100000000000.''',00000000000029:::::::::::       ",
    "      000000%!!!!!!>*00000=!!!!=*0000000000001-.-000000000001-'.,0000000000000000000000000000033300000000000029::::::::::::       ",
    "         0000+>!!!!!=*0000*=!!!!>00000000000000010000000000000000000000000000000000000000000000000000000000029:::::::::::::       ",
    "          00000+>!!!!!+0000*=!!!!?000000000000000000000000000000000000000000000000000000000000000000000000029::::::::::::::       ",
    "          0000000+>!!=>*0000*>>>>=*0000000000000000000000000000000000000000000000000000000000000000000000029:::::::::::::::       ",
    "          000000000*0000                                                                                                          "
  ],
  "width": 130
}
