{
  "height": 56,
  "legend": {
    "!": "color059",
    "#": "color060",
    "$": "color066",
    "%": "color095",
    "&": "color101",
    "'": "color102",
    "(": "color103",
    ")": "color137",
    "*": "color138",
    "+": "color143",
    ",": "color144",
    "-": "color145",
    ".": "color174",
    "/": "color178",
    "0": "color184",
    "1": "color185",
    "2": "color236",
    "3": "color237",
    "4": "color238",
    "5": "color239",
    "6": "color240",
    "7": "color241",
    "8": "color242",
    "9": "color243",
    ":": "color244",
    ";": "color245",
    "<": "color246",
    "=": "color247",
    ">": "color248"
  },
  "name": "monster-hunter-MH3U-fish-icon",
  "pixels": [
    "                                                                                                                ",
    "                                     44444444444444444444444444444                                              ",
    "                                    4446664666444444444444444444444                                             ",
    "                                   4448'''''''''((((((((((((((((8444                                            ",
    "                                  4468''##'':::':::':::':::':::''8444                                           ",
    "                                  448''833#':':::':::':::':::'::''8444                                          ",
    "                                 448''83333#::':::':::':::':::':'''8444                                         ",
    "                                  448833333''::''::''::''::''::'''''8444                                        ",
    "                                  44453344#::::::(::'''''''''''''''''8444                                       ",
    "                                   444534#:::4#:::(:''''''''''''''''''8444                                      ",
    "                                    4444::::444#(:(:''##77#777#7###''''8444                                     ",
    "                                     444#::44444$::(''77777777777777''''8444                                    ",
    "                                      445853333#:::'((77777777777777#:::'8444                                   ",
    "                                       4555333#::'::((777777777777777#::''8444                                  ",
    "                                        55553#::::':((:#77777777777777#:'''8444                                 ",
    "                                         555#:::'::'((((::##777777777#7#''''8444                                ",
    "                                          4449((''''''''''''::8877777777#:::'8444                               ",
    "                                           4449('''''''''''':::::77777777#::''8444                              ",
    "                                            4449'''''''''''':::::777777777#:'''84444                            ",
    "                                             44444444444444444:::77777777#7#''''!4444                           ",
    "                                             54566665555555555::$7777777!!!!8:665!85444                         ",
    "                                            4554#(((''''''''!5::$7777777!##!6468''''64444                       ",
    "                                           445434#((''''''''55::$7777767#5558:::'''''86444                      ",
    "                                         444653344#(''''''''!5::$77777655#::::::'''''''85444                    ",
    "                                        5556'#44444#::::''''64::(!9!5579:::':::':::':::'(!444                   ",
    "                                       45555'''44444::::''''64:8!55!9(((:':::':::':::'::((94444                 ",
    "                                      4455334''#444#:::##'''4444!9((((((::':::':::':::':((((84444               ",
    "                                     444833344''#4#(::##7#''668:((((75(('::''::''::''::'((((::6444              ",
    "                                     449'833335::::::#7777##5''''''#336('''':::':::':::':::''''84444            ",
    "                                     449''833335::::#7777776!'''''#33336'''':':::':::':::'::'''''64444          ",
    "                                     4448''8335::::#77777775'''''#3333336'''::':::':::':::':''''''86444         ",
    "                                      4468''#5::::##77777757'''''333333336'''::''::''::''::'''''''''8444444     ",
    "                                       4449(((((:#777777!!5(:::':3333333335:'''':::':::':::':::'((((::867444    ",
    "                                        4449((((#7777777!5#(:':::33333333335'''':':::':::':::'::('(':<<<<<44    ",
    "                                         4449(((:#777777!5((::'::333333333335'''::':::':::':::':((('<<<<<<744   ",
    "                                          4459((::#777775#(('::':3333333333335'''::''::''::''::'(''<<<<<<<744   ",
    "                                           4448((((9!!!56''':::'933333333#53335:::::((((**;::':'((<=====<<!44   ",
    "                                            4448((((#!#5'''':'::93333333#::53335::::(((*....'':'(<======<!44    ",
    "                                             4449((((#5!''''::':9333333#::#:53334:::((;.....(':'<=======!44     ",
    "                                              4459(((!5('''''::'933333#':33#:53346::((;.....':'(=======744      ",
    "                                               4449(:48::::':::'#3333#::5333#:53335:''''...*('(;======744       ",
    "                              444444444444444444444964:::':::'::#333#::533333#:53333''''***;('(;======44        ",
    "                             4444444444444444444444448::::':::':''3#::53333333#:53334''''''''(';======44        ",
    "                            44!!!!!!!!!!!!!!!!!!666668::'::''::''''':53335#5333#:#3344''''''('(;======44        ",
    "                            44'':::':::':::'::::::::95((:::':::'''''333369993336::33444:''''''''======44        ",
    "                            44'':':::':::'::$$$$$$$$959(:':::'::''''!33369933339:63344!:''''''''======44        ",
    "                            44''::':::':::':#7777777777(::':::':'<===!3336<636<<63334:==<=<=<<'6======44        ",
    "                            44'''::''::''::':7777777775('::''::'<=====!3336<9<<63333:=======<<'8======44        ",
    "                            44'':::':::':::''#777777776#'''''''<=======!333!<<44444<=========='6======444       ",
    "                            44'':':::':::'::''7777777776''''''<=========!333!44444<<=========='8======:444      ",
    "                            44''::':::':::':''#7777777759''''<===========!3344444<<<=========='6=======:444     ",
    "                            44'''::''::''::''''7777777767'''<=============!3444!<<<<===========68=======9444    ",
    "                            448'::::::::''''(:(#77777#7#5::<===============!336================:47=======:44    ",
    "                            444455555553555':(::7777#7##5:<<================66==================:47=======744   ",
    "                             44452223333335'(:(:'9777#7#75<<=====================================:47=====:44    ",
    "                              4455223333335':(:(''''##77757<==================================<===:47999:444    ",
    "                               444433336##''(((((((((::97766:===================================<<<74444444     ",
    "                                444468'''''#33334#((:(::::965:==================================<<:4444444      ",
    "                                 4448'''''#33333#((((:((::::55:==============================<==<744            ",
    "                                  4468'''#33333#((((:(:::::::55:==============================='444             ",
    "                                   4449(!333257:::::::::::::::647<<<<<<<======================:444              ",
    "                                    444655555777888888888888888457<<<<<<=====================7444               ",
    "                                     44444445555444444444444444455557:<<===================:4444                ",
    "                                      4444445555444444444444444455::7755%&;===============:444                  ",
    "                                                               446::777777557:==========<!444                   ",
    "                                                               446::7777777977578'=====:444                     ",
    "                                                               446::7777779(::::8558::7444                      ",
    "                                                               446::777779((::::'''874444                       ",
    "    4444444444                                  4444444        446((####$'('''''''''944                         ",
    "   444444444444                        44444444444444444       446((''''(''(''''''''944                         ",
    "  447'''''''944                      4444444444877'';;844      446(('''''(''''''''''944                         ",
    "  44'>>>>>>>;4444                   44587::=;>>>,,,,>>844      448((''''''($66665555644                         ",
    "  44;>>>,,,,:55544444444444       4447>>>>>>>>>>>>>>--854      45!(('('':::64444444444                          ",
    "  44;>>>,>,><775555444444444444444447>>>>>>;8888888888854       559(''('::644 4                                 ",
    "  44;>>>,,>,<77788888!!!!5554444444'>>>>>>>;8888888888854       5559(''(:644                                    ",
    "  44;>>>,>,,<77:888888888888887777'>>>>>>>><::::::::8;854        555:(':644                                     ",
    "  44'>>>,,,,>:888888888888888888899:''<<<>>>>>>>>>>>--854444444   444::644                                      ",
    "  44'>>>,>,>>>:8888888888888888888888888888::::<<<>>--8544444444444444644                                       ",
    "  444'>>,,>,>>><88888888888988888888888888888888888888888!!!!55544444444444444444 444444444444444444            ",
    "   444'>,>,,>>>><888888888'':888888888888888888888888888888888888877664454444444444444444444444444444           ",
    "    4449,,,,,,,,><888888::))&999888888888862222688884222288888888888888888877!!6555;<<<<<<,<====<<<54           ",
    "     4447,,,,>,>>>>:888::)//+&9988888888888622226888842222888888888888888888888888;>>>>>,,,,====<<<54           ",
    "       447,,,,>,>>>>989:)///0+&988888888888862222688884222288888888888888888888888>>>>>>:88888887:754           ",
    "        447,,>,,>>>>;88:+///00&98888888888888622226888842222788888888888888888888;>>>>>>:888888877:54           ",
    " 44433334447<>>>,,,,<889&///1+&#888888888888886222268888422238888888888888888888:>>>,,,,;9999999'7'44           ",
    " 44777777774!>>>,>,><888&+//+&##888888888888888622226888842233888888888888888888=>>>,>,>>>>>>>>>,,,44           ",
    " 47,>>>>>>>>>>>>,,>,<8889&&&&&##88888888888888822224888862223588888888888888888:>>>>,,>,>>>>>>>>,'744           ",
    " 44,>>>>>>>>>>>>,>,,<8889999#&##8888888888888822222#888622225888888888888888888,>>>>,>,,>>>>>>>94444            ",
    " 47>,,,,,,,,,,,,,,,,<888888888888888888888888222228888!32224888888888888888888<>,,,,,,,,>>>>=744444             ",
    " 47>,>,>,>,>,>,>,>,><88888888888888888888887222248888!332248888888888888888888>>,>,>,,,,>>'744444               ",
    " 47>,,>,,,>,,,>,,,>,<88888888888888888888885444488888555468888888888888888888<>>,,>,,,,>'44444                  ",
    " 47>,>,,,>,,,>,,,>,,<88888888888888888888888888888888888888888888888888888888:>>,>,,,,,>'744444                 ",
    " 45666798888888888888888888:<::88888888888888888888888888888888888888888888888>>,,,,,,,,>>=&444444              ",
    " 4444444888888888888888888:>>>>><::8888888888888888888888888888888888888888888<>,>,>,>,>>>>>>;84444             ",
    "   4  4458888888888888888:>>>>>>>>>><::8888888888888888888888888888888888888888>,,>,,,>,>>>>>>>>'744            ",
    "       45578888888888888:>>>>>>>>>>>>>>><':888888888888888888888888888888888888<,>,,,>,,>>>>>>>>,,744           ",
    "        444888888888888:,,,,,,,,,,,,,,,,,,,,<::88888888888888888888888888888888:>>>>>>><:9:9:9:98'844           ",
    "         4458888888888:>,>,>,>,>,>,>,>,>,,,,>>>><::88888888888888888888888888888>>>>>>>:8888888888844           ",
    "          44488888888:>>,,>,,,>,,,>,,,>,,,,,>>>>>>>><::8888888888888888888888888'>>>>>>:8888888886844           ",
    "           444888888:>>>,>,,,>,,,>,,,>,,,,,,>>>>>>>>>>>><':8888888888888888888889>>>>>><''''''''''844           ",
    "            4458888:>>>>,,,,,,,,,,,,,,,,,,,,,,,,>>>>>>>>>>>>>''888888888888888888'>>>>>>>>>>>>>>>>744           ",
    "             444444:>>>>,>,>,>,>,>,>,>,>,>,>,>,>>>>>>>>>>>>>'885555554545454545448''''''''''''''''744           ",
    "              444444'>>>,,>,,,>,,,>,,,>,,,>,,,>,>>>>>>>'77445558855544444444444444444444444444444444            ",
    "                  443'>>,>,,,>,,,>,,,>,,,>,,,>,,><'87444477'>>>>-;554            444444444444444444             ",
    "                   444:,>>>>>>>>>>>>>>>>>>>>=::74444!&<<,,,,>>>>,,'44                                           ",
    "                    444:>>>>>>>>>>>>>>>>'774444447,,>>>>,>,>>>>>,,,44                                           ",
    "                     444'>>>>>>>>>>;774444444444447,>>>>,,>,>>>>,7444                                           ",
    "                      443'>>>>;&84444444444      444<>>>,>,,>><84444                                            ",
    "                       444885444444444            444:,,>>>><!4444                                              ",
    "                        444444444                  4447,>>'74444                                                ",
    "                          44                         444774444                                                  ",
    "                                                      444444                                                    "
  ],
  "width": 112
}
