{
  "height": 14,
  "legend": {
    "!": "181818",
    "#": "704060",
    "$": "808090",
    "%": "882810",
    "&": "a87898",
    "'": "c89858",
    "(": "c8c8c8",
    ")": "d8a8c8",
    "*": "e8b018",
    "+": "f8e078",
    ",": "f8e840",
    "-": "f8f868",
    ".": "f8f8f8"
  },
  "name": "pokemon-emerald-I-013-weedle-shiny",
  "pixels": [
    "                ((                ",
    "                (.$$              ",
    "                (...$!$           ",
    "                 (....($          ",
    "      $$         $(..((!          ",
    "     $.($         $((($!!!        ",
    "     (.($          $$$$%**!       ",
    "    $..(($            %,,*%!      ",
    "    (...($%!!         %,,%**!     ",
    "   $....(($**%!        %%,,**!    ",
    "  *$....(($****!        %,,%%%    ",
    " *--$..(($*,,***!       %,%,,*!   ",
    " ,--,$$$$*,,,,**%        %,,,**%  ",
    ",------,,,,,,,,**%       %,%%%%!  ",
    ",------,,,,,,,,**!        %,,,,!  ",
    "*,----,,,,,,,,,**!%*     %%*,,**% ",
    "*.!,,,,,,,.!,,,**!--%%%%%,,,%%**! ",
    "*!!,,,,,,,!!,,,**!-,,%-,%%,,,,%*! ",
    "*,,#####,,,,,,***!,,,*%,,*%,,**%!!",
    "*,#+++)&%,,,,,**%%,,**%,,*%****!)!",
    " *#++))&#,,,,***!*****!,***%**-!! ",
    " %#))&&&#,,****%!*****!****!*'-%  ",
    "  %!!!!#******%!''****!***'!'-%   ",
    "   %%********%!---''''!''--!##!   ",
    "     %!!!!!!%-----##-!'-##-!)&!   ",
    "           #)%---#)&!!-#&&# !!    ",
    "           !))!!!!&&!*!!)&!       ",
    "            !!   !!!    !!        "
  ],
  "width": 34
}
