{
  "height": 26,
  "legend": {
    "!": "101010",
    "#": "183800",
    "$": "406010",
    "%": "606060",
    "&": "685048",
    "'": "688838",
    "(": "90b060",
    ")": "a08880",
    "*": "c8b0a8",
    "+": "d0d0d0",
    ",": "e8d8d0",
    "-": "f8f8f8"
  },
  "name": "pokemon-emerald-I-041-zubat-shiny",
  "pixels": [
    "         #                                   ",
    "        #!                             ###!!!",
    "       #'!                          ##'$$&&& ",
    "      #''!                       #!#'$#))))  ",
    "     #''$!                     #$''###))))   ",
    "     $''$!                   #$''##)))**)    ",
    "    #'''$!                 #$''##)))***)     ",
    "    $'''$#                #''##)))***,&      ",
    "   #''''$$#              #('#)))***,,,)      ",
    "   $'''''$!             #((#)))***,,,&       ",
    "  #'''''''$#            #($#))***,,,,)       ",
    "  #'''((###$#!           !$#))***,,,)        ",
    "  $'(($#$$$$!             #$###**,,,&        ",
    " #'''$$$$$$!              !$$$$$##*,&        ",
    " #''$$$$$$$!              !$$###$$#,&        ",
    " ##'''$$$$$!              !$#))))#$$&        ",
    "   ##'''$$$#              !$#))****#$        ",
    "     ##''$$$!             !$#)****&!#        ",
    "       #'$$$#             #$#)**&!           ",
    "        #'$$$!           #$#)**!             ",
    "         #$$$#         ###$#)*!              ",
    "          #$$$!      #$''!#))!               ",
    "$$#        !$$$!   #$''&)!))&                ",
    "$''#!       !$$$!!#''&)**!))!                ",
    "&&&''#!      !$$$#'$&&,,#))&                 ",
    "&*)&'$$! $##!!!$!'$&)*&,!))!                 ",
    " &*&&$$##(((''$!'$$&)*&#))&                  ",
    " &,&*&$'((('''''$$&)))*!))!                  ",
    "  &,&)#((('''''$$$&)))!$))!                  ",
    "   &*#'(''''''$$$$$##!!$$$#!                 ",
    "    &#''''''''$$$$$$$$#$$$$$!                ",
    "     #######'''$$$$$$$$$$''$$                ",
    "     %+!!!!+###'$$$$$$$$''''$#               ",
    "     %-!!!!-!!!#$$$$$$$$''''$!               ",
    "      !!!!!!!!!!#$$!$$$$''''$!               ",
    "        !!!!!!!!#$##$$$$$''$$!               ",
    "        !!%%%!!!!!!$$$$$$$$$!                ",
    "       %!%%%!-!#!  !$$$$$$$!$                ",
    "       %+!%%!+'!    !#$#!!!$$#               ",
    "        %!!!!!!       #$!  #$!               ",
    "                      #$!  #$!               ",
    "                      $!    $!               ",
    "                     #$#    $!               ",
    "                     $#     $!               ",
    "                     $!     $!               ",
    "                    $#      $#               ",
    "                    $!     $#                ",
    "                   $!      $!                ",
    "                   !       $!                ",
    "                           #                 ",
    "                           !                 "
  ],
  "width": 45
}
