{
  "height": 30,
  "legend": {
    "!": "000000ff",
    "#": "403820ff",
    "$": "807058ff",
    "%": "b88830ff",
    "&": "c06040ff",
    "'": "c0b090ff",
    "(": "d88048ff",
    ")": "d8d0b0ff",
    "*": "e8a048ff",
    "+": "f8c868ff",
    ",": "f8f0f0ff"
  },
  "name": "pokemon-leafgreen-III-264-linoone-shiny",
  "pixels": [
    "                                  $!!              ",
    "                               $!!,)&!             ",
    "                             $!,,)&!$              ",
    "                            !),,))!                ",
    "                        !  !(,,)))$                ",
    "                       !(!!(,,),)!                 ",
    "                       !(#(,,),))$                 ",
    "                       #((*,,)))!                  ",
    "                      !(((,,))))$                  ",
    "                      !((*,,)))!                   ",
    "                      !((*,,)))!                   ",
    "                      #((,,,)))!                   ",
    "                     !&#(,,,,))$                   ",
    "                     !&#(,,,,)))!                  ",
    "                     !&&(,,,,,))!                  ",
    "                      #(((,,,,,))!                 ",
    "                      !((&,,,*,,,)!!               ",
    "                       #(&(,,,**,,,,!!             ",
    "                       !(&&,,,,((,,,,)!!           ",
    "                        #&&(,,*(((*,,,)&!!         ",
    "                         #&&,,,(((((,,,)&&!        ",
    "                          !&&,,*(((((,,,)&&!       ",
    "                          !&&,,,((*((*,,,)&&!      ",
    "                           !&,,,(*(*((,,,))&&      ",
    "                           !&,,,*(*((((,,,)&&!     ",
    "                          !&,,,*(*(*((&,,,))&(!    ",
    "                          !&,,,(*(((((&,,,))(&!    ",
    "                          !,,,(((((((&(,,,)))(&!   ",
    "                         (,,,(((((((&&,,,),))&(!   ",
    "                        (,,,((((((&&&,,,,,)))(&(!  ",
    "                      ((,,(((((&&&&(,,,,,),))&(&!  ",
    "                    '',,(&&&&&&&&(,,,,,,),))&&&(!  ",
    "        '( $     ''',,(&&&&&&&(,,,,,,,,),),)&&(&!  ",
    "       ' $  $  '',,((&&&&&&(,,,,,,,,,,),),)&&&&&!  ",
    "       '    $( (((&&&&&&(,,,,,,,,,,,))))))&&&&&(!! ",
    "      '   '',*&&,&$(,,,,,,,,,,,,,,))))))(&&&&&()!$ ",
    "      ' '',*&&,',',$,,,,,,,,,,(&()))))(&&&&&&())!$!",
    "      '',*&&&',,,))')))),,,(&&&)))))(&&&&&&()))$$$!",
    "      (,*&&&&',,,)))))))(&&&&())))(&&&&&())))))!$$!",
    "     (,*((&(',,,)))))(&&&&&())))))))))))))))))$$$$!",
    "    (&(((*)),,,,))(&&&&&&&&&&&&())))))))))))))!$)$!",
    "   (&((((&&*)))(&&&&&&&&&&&&&()))))))))))))))!)$,! ",
    "  (,&((&),,,(&&&&&&&&&&&&&&()))))))))))))))'!$,!,! ",
    "  (,&&),,,(&&&&&&&&&&&&&&&&&())))))))))))''!  $ !  ",
    " !,(&,,,(&###&&&&&&&&&&&&&&&&&())))))))''$!        ",
    " !,(,,(&!,%+#&&&&(())))'$$$)))))))))''$!!          ",
    "!,,,,(&!%!%!()))))))))))),,$)))))''$!!             ",
    "!#()))))!!!)))))))))))),'$$))''$!!!                ",
    "!###()))))))))))))),,,,,,,,''!!                    ",
    " !##)))$##''''''$#$$$$$$$$''$                      ",
    "    !#$'''''$!!!    $$''''''!                      ",
    "     !$!!!!!##    $$'''''''!                       ",
    "    !$$$$$$#    $')))'''''$                        ",
    "   !$$$$$#    $')))))'''$!                         ",
    "   $',$##    $'))))''$!!                           ",
    "  $',,#     ',,$$)'!!                              ",
    "  $,!!     ',$$,,!!                                ",
    "   !      ',$,,!!                                  ",
    "          $$,$!                                    ",
    "           $!                                      "
  ],
  "width": 51
}
