{
  "height": 18,
  "legend": {
    "!": "181818",
    "#": "605050",
    "$": "909000",
    "%": "a05088",
    "&": "b0a098",
    "'": "b880a0",
    "(": "c0c058",
    ")": "d8a0c0",
    "*": "d8d0a0",
    "+": "e0d0e8",
    ",": "f0f000",
    "-": "f8f8d0",
    ".": "f8f8f8"
  },
  "name": "pokemon-leafgreen-III-265-wurmple-shiny",
  "pixels": [
    "                     %%       ",
    "                    ')'%      ",
    "                    ')'#      ",
    "                    ')'#      ",
    "                   %))'#      ",
    "                  %)))''%     ",
    "             ($   )))'''#%%#  ",
    "             $,$ #)))'''%%%!  ",
    "             $,,#)))'''''#!   ",
    "             $,,,#))'''''#    ",
    "            %$(,(%'''##%%#    ",
    "           #))%%%'''%,,#%%#   ",
    "           #'''''''%,,,(#%'#  ",
    "     $     &&''''&&#,##(#%''# ",
    " $  $,$    &-*&&*--#,##(#%%%! ",
    "$,$ $,$   &---*----#,##(#%%%# ",
    "#,$ $,(   #--*-----*&((&#%%#  ",
    "#,,$$,,$  #*-&------#((#%%%#  ",
    " $,#$,,$  #**#*******##&%%%%# ",
    " #,,($(($  #*#**********%%'''#",
    " #(((#(($   ##&***&#***&%%%''!",
    "  #((#(#%#    ####&****%%%%%! ",
    "  #(%%%%%%#   '********%%%%#  ",
    "   #%%%%''''##'&-----**&%%%#  ",
    "   %%%''%%'''%'&-----***%%%'# ",
    "   %%%%%%%''%%&#&----*&##%'''#",
    "  #'%%%%%'%%%#..&&&&&&#..%%%'!",
    " #''%%''%%%%#..+&----*#+.!%%! ",
    " #'%%#''%%''%###*---***&!!%!  ",
    "  #%#%##%#''%%#*********%%%!  ",
    "   %&*#&&%##%%%#&*****&#%%#   ",
    "   #+&++#&&%%%***#####&*%%!   ",
    "   ###.+#.+&**#&*******&#!    ",
    "     #!!..+#!#.+&*****&..#    ",
    "        !!! !.++#!!!!!++.!    ",
    "             #!!      !!!     "
  ],
  "width": 30
}
