{
  "height": 64,
  "legend": {
    "!": "color044",
    "#": "color045",
    "$": "color059",
    "%": "color067",
    "&": "color073",
    "'": "color074",
    "(": "color089",
    ")": "color095",
    "*": "color096",
    "+": "color102",
    ",": "color131",
    "-": "color132",
    ".": "color137",
    "/": "color138",
    "0": "color144",
    "1": "color145",
    "2": "color167",
    "3": "color168",
    "4": "color174",
    "5": "color175",
    "6": "color181",
    "7": "color182",
    "8": "color187",
    "9": "color188",
    ":": "color217",
    ";": "color218",
    "<": "color224",
    "=": "color240",
    ">": "color241",
    "?": "color242",
    "@": "color243",
    "A": "color244",
    "B": "color245",
    "C": "color246",
    "D": "color247",
    "E": "color248",
    "F": "color249",
    "G": "color250",
    "H": "color251",
    "I": "color252",
    "J": "color253",
    "K": "color254",
    "L": "color255"
  },
  "name": "monster-hunter-MHO-pink-rathian-icon",
  "pixels": [
    "                                                                                                                                ",
    "                                                                                                                                ",
    "                                                       46                                                                       ",
    "                                                     <226                                  <                                    ",
    "                                                    ;2226                              <632:                                    ",
    "                                                   <22226                            :32223                                     ",
    "                                                  <222226                         <4222222<                                     ",
    "                                                  3222226                       <422222225                                      ",
    "                                                 62222226                      5222222222                                       ",
    "                                                 22222226                    :2222222222:                                       ",
    "                                                522222226                   422222222223                                        ",
    "                                                222222226                 ;222222222222<                                        ",
    "                                               :222222226                62222222222224                                         ",
    "                                               3222222226               42222222222222<                                         ",
    "                                               2222222226              322222222222225                                          ",
    "                                              <2222222226             322222222222222                                           ",
    "                                              :2222222226            322222222222222:                                           ",
    "                                              :222222222:           4222222222222223                         ;:54433334456;<    ",
    "                                     L        <444444444<          <444444444444444<                    :432222222222222225     ",
    "                                    G)J       <444444444<         <444444444444444;                  63222222222222222223<      ",
    "                                   E$$>J      <444444444<        <5444444444444445                <:4422222222222222222:        ",
    "                                 LC$$$$)J     <444444444<        6444444444444444<              <644444222222222222224          ",
    "                                LB$$$$$$)J    <444444444<       ;4444444444444445             <644444444222222222222<           ",
    "                                C$$$$$$$$)K   <444444444<      <4444444444444444<           <:444444444442222222224             ",
    "                                @$$$$$$$$$H   <444444444<      64444444444444446           <544444444444432222222:              ",
    "                                @$$$$$$$$$H   <444444445<     <4444444444444444<          :444444444444444222222<               ",
    "                                @$$$$$$$$$H   <44444446<     <44444444444444446         <6444444444444444422224                 ",
    "                            K   @$$$$$$$$$H   <444444:       :4444444444444444<        <5444444444444444443226                  ",
    "                           GH   @$$$$$$$$$H   <44444<       <44444444444444445        <444444444444444444442:                   ",
    "                          9$H   @$$$$$$$$$H   ;4444<        <5555555555555555<       <444444444444444444444;                    ",
    "                         K)$H   @$$$$$$$$$I   ;445<                                 <444444444444444444445<                     ",
    "                         C$$H   @$$$$$$$C9    <46<                                 <544444444444444444444<                      ",
    "                        I$$$H   @$$$$$BJ      <:       6:                          644444444444444444444<                       ",
    "                       L@$$$H   @$$$@I        <       52:                         :44444444444444444444<                        ",
    "                       H$$$$H   @$$1L    ;:          522:                        <444444444444444444446                         ",
    "                       +$$$$H   @@J     ;2:         4222:    <;;;;;;;;;;;;;;;<  <544444444444444444444<                         ",
    "                       ?$$$$H   H      :22:        42222:    4222222222222222<  <::::::::::::::::::::<                          ",
    "                       ?$$$$H         :222:       322222:    422222222222222<                                                   ",
    "                       ?$$$$H        :2222:     <3222222:    42222222222223<                                                    ",
    "                       ?$$$$I       :22222:    <22222222:    4222222222223<                                                     ",
    "                       ?$$)I       6222222:    322222222:    422222222223                              <<<<<                    ",
    "                       ?$AK        3222222:    322222222:    42222222223                        <<;:6544444445434:              ",
    "                       ?CL   <;    3222222:    322222222:    4222222224        <<<<<<<<<<    <:5444444444444442222236           ",
    "                       G     22:   3222222:    322222222:    422222224       <322222222225  ;44444444444444444222222224<        ",
    "       E                    :22:                                            <3222222222225  ;4444444444444444422222222224       ",
    "       ?G                  <222:                                           <22222222222225  ;44444444444444444222222222222:     ",
    "       ?@   HHHHHHHHHH7;;;62222:                                          <222222222222225  ;4444444444444444422222222222224    ",
    "       ?$C  G$$$$$$$$$,22222222:                                         <2222222222222225  ;444444444444444442222222222234:    ",
    "       ?$$F  1$$$$$$$$,22222222:    KKKKKK     KKKKKK     KKKKKKK       <22222222222222225  ;4444444444444444422222234:         ",
    "       ?$$@   1$$$$$$$,22222222:    G00000I    G00000I    G00000I      ;222222222222222225  ;444444444444444442235<             ",
    "       ?$$$C   1$$$$$$,22222222:    G00000I    G00000I    G00000I      4222222222222222225  ;4444444444444446;<                 ",
    "       @$$$$1   F$$$$$,22222222:    G00000I    G00000I    G00000I      3222222222222222225  ;4444444444446<<                    ",
    "       @$$$$>G   H>$$$,22222222:    G00000I    G00000I    G00000I      4222222222222222226  ;4444444446<<                       ",
    "       B$$$$$?G   I@$$,22222222:    G00000I    G00000I    G00000I                           ;4444444:<                          ",
    "       D$$$$$$?H    C$,22222222:    G00000I    G00000I    G00000I                           ;44445<                             ",
    "       F$$$$$$$?H    1,22222222:    G00000I    G00000I    G00000I   ;::::::::::::::::::::;  ;445<                               ",
    "       H$$$$$$$$@H    ;32222222:    G00000I    G00000I    G00000I   3222222222222222222224  ;4:<                                ",
    "        +$$$$$$$$@H     :322222:    G00000I    G00000I    G00000I   3222222222222222222224  <<                                  ",
    "        F$$$$$$$$$@H      :4222:    G00000I    G00000I    G00000I   3222222222222222222224                                      ",
    "         A$$$$$$$$$F         :4:    G00000I    G00000I    G00000I   3222222222222222222224                                      ",
    "         G>$$$$$$$$D                G000009    H000009    G00000I   3222222222222222222224  <<<<<<<<                            ",
    "          1$$$$$$$$B                                      G00000I   3222224         422224  ;4444444456:<<                      ",
    "           1>$$$$$$?                                      G00000I   3222224         422224  ;444444444444446<<                  ",
    "            G+$$$$$$     <<<<<<<<<<<<<                    G00000I   3222224  <;;;<  422224  ;4444444444444444445<               ",
    "              GD+???H  ;222222222222226       KJJJJJJK    G00000I   3222224  42226  422224  ;444444444444444442224<             ",
    "                      ;222222222222222,/      F000000I              3222224  42226  422224  ;44444444444444444222225            ",
    "  ;;;;;;;;;;;        ;2222222222222222,)/     F000000I              3222224;;42225  422224  ;444444444444444442222222<          ",
    "  52222222222:      <22222222222222222,))/    J000000I              32222222222225  422224  ;4444444444444444422222222:         ",
    "   6222222222:     <222222222222222,,,,)))/    K00000I              32222222222225  422224  ;444444444444444442222222225        ",
    "    622222222:     3222222222222222)==)))))/    K1000I              32222222222225  422224  ;4444444444444444422222222225       ",
    "     62222222:    32222222222222222)==))))))/     G00I              32222222222225  422224  ;44444444444444444322222222226      ",
    "      6222222:   ;22222222222222222))))))))))/     H0I              32222222222225  422224  ;44555555444444444322222222222<     ",
    "       622222:   ;22222222222222222222,)))))))/                                     422224             <<<<;:63222222222222     ",
    "        62222:   ;22222222222222222222,))))))))/                                    422224  <<                 ;532222222225    ",
    "         6222:   ;222222222222222222223)))))))))/                ;;;;;;;;;;;;;;;;;;;422224  :446:<<                <63222222    ",
    "          622:   ;2222222222222222222266)))))))))/             :22222222222222222222222224  :4444446;<                 :42225   ",
    "           62:   ;222222222222222222226 6)))))))),             422222222222222222222222224  :4444444446<                  :32   ",
    "            6:   ;222222222222222222226  6))))))),             322222222222222222222222224  :444444444445<                  <   ",
    "                 ;222222222222222222226   6)))))),             322222222222222222222222224  :44444444444445<                    ",
    "                 ;222222222222222222226    6))))),             322222222222222222222222224  :444444444444444:<                  ",
    "                 ;222222222222222222226     6)))),             322222222222222222222222224  :44444444444444445<                 ",
    "                 ;222222222222222222226      6))),             322222222222222222222222224  :4444444444444444436                ",
    "           :::::::222222222222222222226       ,)),             422222222222222222222222224  :44444444444444444325               ",
    "           2222222222222222222222222226       ,)),             F0000000000I                 :444444444444444443225              ",
    "           2222222222222,,,,,2222222./0000I   ,)),             F0000000000I                 :444444444444444443222:             ",
    "           2222222222222!####',2222/000000I   ,)),             F0000000000I                    <<<<:644444444432222<            ",
    "           2222222222222'#####!,222/000000I   ,)),             F0000000000I                           <;544444322223            ",
    "           3222222222222-######!222/000000I   ,)),             F0000000000I                              <:444322222:           ",
    "            3222222222222%######+222,.0000I   ,)),             F0000000000I                 <<<            <;53222222           ",
    "             3222222222222######&222226       ,)),K            F0000000000I        KJK      :445:<            6222222:          ",
    "              322222222222*#####%222226       ,)),F0K          10000000000I        00H      :444445;<          <322222          ",
    "               322222222222'####-222226       ,)),F01          1000H  H000HJJKKKKKI00H      :44444444:<          62222<         ",
    "                32222222222,###'2222226       ,)),F00G         1000I  K00000000000000H      :4444444445<          <2225         ",
    "                 32222222222+!!,22222/0FI     ,)),F000H        1000I   G0000000000000H      :44444444444:           423         ",
    "                  322222222222222222/0000EI   ,)),F0000I       1000I   9000000000000H       :4444444444446           52         ",
    "                   3222222222222222/000001    ,)),F000009      1000I                        :44444444444446           6<        ",
    "                    32222222222222/00000F     ,)),F000000J     1000I                        :444444444444446                    ",
    "                     322222222222/00000F      ,)),F0000000K    1000I                        :4444444444444444                   ",
    "                      3222222222/0000009      ,)),F00000000    1000I                        <:664444444444422;                  ",
    "                       32222222/00000009      ,)),F00000000F   F000I                             <;64444444222                  ",
    "                        444444/000000009      ,)),F000000000G  F0000J         KIG0H                 <:44442222:                 ",
    "                     66  90000000000000G      ,)),F0000000000H G000009JJJJJJJJG000H                   <:4322222                 ",
    "              800000,((,6 90000000000000G     ,)),F00000000000IK100000000000000000H                     <322222<                ",
    "             800000,((((,6 90000000000000G    ,)),F000000000000JK10000000000000000H          <<           622224                ",
    "            800000,((((((,6 90000000000000G       F0000000000000JK100000000000000EK         :44:           <3222                ",
    "           800000,((((((((,6 910000000000009      G0000000000000I K1000000000000F          :44445<           522                ",
    "          800000,((((((((((,6                                                             :4444445<           :2;               ",
    "         800000,((((((((((((,6                                                           ;444444445<           <;               ",
    "        800000,((((((((((((((,6                                                          <:44444444:                            ",
    "       800000,((((((((((((((((,6                                                           <54444442:                           ",
    "       00000,((((((((((((((((((4  <<<<<<<<<<<<   <<<<<<<<<<<<   <<<<<<<<<<<<  <<<<<<<<<<<<  <64444222                           ",
    "       00000((((((((222222222224  54444444444<   64444444444<   64444444444<  <4444444444:    64422226                          ",
    "       00000((((((((222222222224  54444444444<   64444444444<   64444444444<  <4444444444:     6222222                          ",
    "       00000((((((((222222222224  54444444444<   64444444444<   64444444444<  <4444444444:      322222<                         ",
    "       00000((((((((222222222224  54444444444<   64444444444<   64444444444<  <4444444444:       222226                         ",
    "       00000((((((((222222222224  54444444444<   64444444444<   64444444444<  <4444444444:       <22223                         ",
    "       00000((((((((222222222224  54444444444<   64444444444<   64444444444<  <4444444444:        <2222                         ",
    "       00000.(((((((222222222224  54444444444<   64444444444<   64444444444<  <4444444444:         ;222                         ",
    "       800000.((((((((((((((((,   22222222222:   222222222224   222222222225  422222222223          622<                        ",
    "        800000.((((((((((((((,    22222222222:   222222222224   222222222225  422222222223           42<                        ",
    "         800000.((((((((((((,     222,///,222:   2222///,2224   2222///,2225  4222,///2223            2;                        ",
    "          800000.((((((((((,      222,000/222:   3222000/2225   3222000/2226  5222/0002224            <<                        ",
    "           800000.((((((((,          H000G          J0000          J0000          0000J                                         ",
    "            800000.((((((,           H000G          J0000          J0000          0000J                                         ",
    "             800000.((((,            H000G          J0000          J0000          0000J                                         ",
    "              800000/((,             H000G          J0000          J0000          0000J                                         ",
    "                                                                                                                                ",
    "                                                                                                                                "
  ],
  "width": 128
}
