{
  "height": 36,
  "legend": {
    "!": "1f1f0f",
    "#": "2f1f0f",
    "$": "2f2f1f",
    "%": "3f2f0f",
    "&": "3f2f1f",
    "'": "3f3f0f",
    "(": "4f3f1f",
    ")": "5f4f2f",
    "*": "6f5f3f",
    "+": "6f6f1f",
    ",": "6f7f1f",
    "-": "7f4f1f",
    ".": "7f7f3f",
    "/": "7f903f",
    "0": "90903f",
    "1": "90a03f",
    "2": "a0b04f",
    "3": "b0c04f",
    "4": "f0a000"
  },
  "name": "monster-hunter-MH4U-rhenoplos-icon",
  "pixels": [
    "                                                                        ",
    "                                                                        ",
    "                                                            !!          ",
    "                                                            !!          ",
    "                !!        !!        !!                    !!!!!!        ",
    "                !!        !!        !!                    !!!!!!        ",
    "              $$!!!!    $$!!$$    !!!!$$              !!2211!!1122!!    ",
    "              $$!!!!    $$!!$$    !!!!$$              !!2211!!1122!!    ",
    "              !!!!!!%%  !!!!!!  %%!!!!!!            !!!!!!222222!!!!!!  ",
    "              !!!!!!%%  !!!!!!  %%!!!!!!            !!!!!!222222!!!!!!  ",
    "            $$!!!!%%--          --%%!!!!$$            !!11//!!//11!!    ",
    "            $$!!!!%%--          --%%!!!!$$            !!11//!!//11!!    ",
    "  ,,++      %%!!%%--!!  !!!!!!  !!--%%!!%%      ++22    22!!!!##22      ",
    "  ,,++      %%!!%%--!!  !!!!!!  !!--%%!!%%      ++22    22!!!!##22      ",
    "  ,,,,,,++  --%%--!!!!  !!!!!!  !!!!--%%--  ++,,,,22                    ",
    "  ,,,,,,++  --%%--!!!!  !!!!!!  !!!!--%%--  ++,,,,22                    ",
    "        ,,!!!!--!!!!--  !!!!!!  --!!!!--!!!!,,          $$!!!!!!$$      ",
    "        ,,!!!!--!!!!--  !!!!!!  --!!!!--!!!!,,          $$!!!!!!$$      ",
    "  3333  ,,--!!!!!!--%%  !!!!!!  %%--!!!!!!--,,  3333    !!      !!      ",
    "  3333  ,,--!!!!!!--%%  !!!!!!  %%--!!!!!!--,,  3333    !!      !!      ",
    "  3333  ,,!!--!!--%%!!  !!!!!!  !!%%--!!--%%,,  3333      $$!!$$        ",
    "  3333  ,,!!--!!--%%!!  !!!!!!  !!%%--!!--%%,,  3333      $$!!$$        ",
    "  0033  ,,$$!!--%%!!!!  !!!!!!  !!!!%%--%%!!,,  3300    $$!!  !!$$      ",
    "  0033  ,,$$!!--%%!!!!  !!!!!!  !!!!%%--%%!!,,  3300    $$!!  !!$$      ",
    "    33  ,,  !!%%!!&&    !!!!!!    ((!!%%!!$$,,  33      !!  $$  !!      ",
    "    33  ,,  !!%%!!&&    !!!!!!    ((!!%%!!$$,,  33      !!  $$  !!      ",
    "    00  ,,  !!!!  $$!!  !!!!!!  !!##))!!!!  ,,  00        !!!!!!        ",
    "    00  ,,  !!!!  $$!!  !!!!!!  !!##))!!!!  ,,  00        !!!!!!        ",
    "        ,,  !!  !!!!!!  !!!!!!  !!!!!!  !!  ,,          !!!!!!!!!!      ",
    "        ,,  !!  !!!!!!  !!!!!!  !!!!!!  !!  ,,          !!!!!!!!!!      ",
    "      !!,,++  !!!!!!!!  !!!!!!  !!!!!!!!  ++,,!!      !!!!!!!!!!!!$$    ",
    "      !!,,++  !!!!!!!!  !!!!!!  !!!!!!!!  ++,,!!      !!!!!!!!!!!!$$    ",
    "    !!!!  ,,    !!!!!!  $$!!$$  !!!!!!    ,,  !!!!              !!!!    ",
    "    !!!!  ,,    !!!!!!  $$!!$$  !!!!!!    ,,  !!!!              !!!!    ",
    "  !!!!!!$$    ,,  !!!!    $$    !!!!  ,,    $$!!!!!!  $$!!!!!!$$  !!    ",
    "  !!!!!!$$    ,,  !!!!    $$    !!!!  ,,    $$!!!!!!  $$!!!!!!$$  !!    ",
    "    !!!!!!  ,,,,,,44  $$!!  $$!!  44,,,,,,  !!!!!!  !!%%------%%!!      ",
    "    !!!!!!  ,,,,,,44  $$!!  $$!!  44,,,,,,  !!!!!!  !!%%------%%!!      ",
    "      !!!!  2222,,,,  !!!!!!!!!!  ,,,,2222  !!!!  !!!!--%%!!!!--%%!!    ",
    "      !!!!  2222,,,,  !!!!!!!!!!  ,,,,2222  !!!!  !!!!--%%!!!!--%%!!    ",
    "        !!  2222,,,,$$!!!!!!!!!!$$,,,,2222  !!  !!--!!%%--!!!!!!--!!!!  ",
    "        !!  2222,,,,$$!!!!!!!!!!$$,,,,2222  !!  !!--!!%%--!!!!!!--!!!!  ",
    "        ,,  !!,,,,,,!!!!!!!!!!!!!!,,,,,,!!  ,,  $$!!--!!%%--!!!!--!!!!  ",
    "        ,,  !!,,,,,,!!!!!!!!!!!!!!,,,,,,!!  ,,  $$!!--!!%%--!!!!--!!!!  ",
    "      !!,,  !!!!,,**!!!!!!!!!!!!!!**,,!!!!  ,,!!  !!!!--!!!!!!--%%!!    ",
    "      !!,,  !!!!,,**!!!!!!!!!!!!!!**,,!!!!  ,,!!  !!!!--!!!!!!--%%!!    ",
    "    !!!!,,      33****!!!!!!!!!!****33      ,,!!!!  !!!!------%%!!      ",
    "    !!!!,,      33****!!!!!!!!!!****33      ,,!!!!  !!!!------%%!!      ",
    "  !!!!!!,,,,,,++  33****$$!!$$****33  ++,,,,,,!!!!!!  $$!!!!!!!!        ",
    "  !!!!!!,,,,,,++  33****$$!!$$****33  ++,,,,,,!!!!!!  $$!!!!!!!!        ",
    "    !!!!,,,,,,,,  3333**********3333  ,,,,,,,,!!!!  !!          !!      ",
    "    !!!!,,,,,,,,  3333**********3333  ,,,,,,,,!!!!  !!          !!      ",
    "      !!,,,,,,,,  003333333333333300  ,,,,,,,,!!    $$!!!!!!!!!!$$      ",
    "      !!,,,,,,,,  003333333333333300  ,,,,,,,,!!    $$!!!!!!!!!!$$      ",
    "        2222,,,,++  33333333333333  ++,,,,2222        !!!!!!!!!!        ",
    "        2222,,,,++  33333333333333  ++,,,,2222        !!!!!!!!!!        ",
    "        ..22,,,,,,    0033333300    ,,,,,,22..        ,,''!!'',,        ",
    "        ..22,,,,,,    0033333300    ,,,,,,22..        ,,''!!'',,        ",
    "          ,,,,,,,,                  ,,,,,,,,          ,,,,,,,,,,        ",
    "          ,,,,,,,,                  ,,,,,,,,          ,,,,,,,,,,        ",
    "          ,,,,,,,,++              ++,,,,,,,,          ,,,,,,,,,,        ",
    "          ,,,,,,,,++              ++,,,,,,,,          ,,,,,,,,,,        ",
    "          ,,,,,,,,,,              ,,,,,,,,,,          ,,,,,,,,,,        ",
    "          ,,,,,,,,,,              ,,,,,,,,,,          ,,,,,,,,,,        ",
    "        ,,,,,,,,,,,,              ,,,,,,,,,,,,        ,,,,,,,,,,        ",
    "        ,,,,,,,,,,,,              ,,,,,,,,,,,,        ,,,,,,,,,,        ",
    "      0033,,33,,3333              3333,,33,,3300      33,,33,,3300      ",
    "      0033,,33,,3333              3333,,33,,3300      33,,33,,3300      ",
    "      3333,,33,,3333              3333,,33,,3333      33,,33,,3333      ",
    "      3333,,33,,3333              3333,,33,,3333      33,,33,,3333      ",
    "                                                                        ",
    "                                                                        "
  ],
  "width": 72
}
